scantechstackvulns/__init__.py
scantechstackvulns/logger.py
scantechstackvulns/utils.py
scantechstackvulns-1.0.3.dist-info/LICENSE
scantechstackvulns-1.0.3.dist-info/WHEEL
scantechstackvulns-1.0.3.dist-info/METADATA
scantechstackvulns-1.0.3.dist-info/RECORD
