Metadata-Version: 2.1
Name: scantechstackvulns
Version: 1.0.3
Summary: 
Home-page: https://github.com/devarajug/getTechStackVulns
Author: Devaraju Garigapati
Author-email: devarajugarigapati@gmail.com
Requires-Python: >=3.8,<4.0
Classifier: Programming Language :: Python :: 3
Classifier: Programming Language :: Python :: 3.10
Classifier: Programming Language :: Python :: 3.8
Classifier: Programming Language :: Python :: 3.9
Requires-Dist: bs4 (>=0.0.1,<0.0.2)
Requires-Dist: lxml (>=4.9.2,<5.0.0)
Requires-Dist: requests (>=2.28.1,<3.0.0)
Requires-Dist: simplexl (>=1.0.2,<2.0.0)
Project-URL: Repository, https://github.com/devarajug/getTechStackVulns
